{"dependencies":[{"name":"tslib","loc":{"line":1,"column":25}},{"name":"../observable/empty","loc":{"line":2,"column":22}},{"name":"../util/lift","loc":{"line":3,"column":24}},{"name":"./OperatorSubscriber","loc":{"line":4,"column":41}}],"generated":{"js":"\"use strict\";\n\nObject.defineProperty(exports, \"__esModule\", {\n  value: true\n});\nexports.takeLast = takeLast;\n\nvar _tslib = require(\"tslib\");\n\nvar _empty = require(\"../observable/empty\");\n\nvar _lift = require(\"../util/lift\");\n\nvar _OperatorSubscriber = require(\"./OperatorSubscriber\");\n\nfunction takeLast(count) {\n  return count <= 0 ? function () {\n    return _empty.EMPTY;\n  } : (0, _lift.operate)(function (source, subscriber) {\n    var buffer = [];\n    source.subscribe((0, _OperatorSubscriber.createOperatorSubscriber)(subscriber, function (value) {\n      buffer.push(value);\n      count < buffer.length && buffer.shift();\n    }, function () {\n      var e_1, _a;\n      try {\n        for (var buffer_1 = (0, _tslib.__values)(buffer), buffer_1_1 = buffer_1.next(); !buffer_1_1.done; buffer_1_1 = buffer_1.next()) {\n          var value = buffer_1_1.value;\n          subscriber.next(value);\n        }\n      } catch (e_1_1) {\n        e_1 = { error: e_1_1 };\n      } finally {\n        try {\n          if (buffer_1_1 && !buffer_1_1.done && (_a = buffer_1.return)) _a.call(buffer_1);\n        } finally {\n          if (e_1) throw e_1.error;\n        }\n      }\n      subscriber.complete();\n    }, undefined, function () {\n      buffer = null;\n    }));\n  });\n}\n//# sourceMappingURL=takeLast.js.map"},"hash":"4703f67be729d2324a03b5cb5ca6ea80"}