{"dependencies":[{"name":"../config","loc":{"line":1,"column":23}}],"generated":{"js":"\"use strict\";\n\nObject.defineProperty(exports, \"__esModule\", {\n  value: true\n});\nexports.errorContext = errorContext;\nexports.captureError = captureError;\n\nvar _config = require(\"../config\");\n\nvar context = null;\nfunction errorContext(cb) {\n  if (_config.config.useDeprecatedSynchronousErrorHandling) {\n    var isRoot = !context;\n    if (isRoot) {\n      context = { errorThrown: false, error: null };\n    }\n    cb();\n    if (isRoot) {\n      var _a = context,\n          errorThrown = _a.errorThrown,\n          error = _a.error;\n      context = null;\n      if (errorThrown) {\n        throw error;\n      }\n    }\n  } else {\n    cb();\n  }\n}\nfunction captureError(err) {\n  if (_config.config.useDeprecatedSynchronousErrorHandling && context) {\n    context.errorThrown = true;\n    context.error = err;\n  }\n}\n//# sourceMappingURL=errorContext.js.map"},"hash":"3f1e275a89364794107dc5fbb4f40f8d"}